py_bes-0.2.3.dist-info/DESCRIPTION.rst
py_bes-0.2.3.dist-info/METADATA
py_bes-0.2.3.dist-info/RECORD
py_bes-0.2.3.dist-info/WHEEL
py_bes-0.2.3.dist-info/metadata.json
py_bes-0.2.3.dist-info/top_level.txt
pybes/__init__.py
pybes/pybes.py
pybes/tests/__init__.py
pybes/tests/test_bes_full.py
pybes/tests/test_bes_preview.py
pybes/tests/test_bes_utils.py
pybes/tests/test_pybes.py
pybes/utils/__init__.py
pybes/utils/bes_constants.py
pybes/utils/bes_full.py
pybes/utils/bes_preview.py
pybes/utils/bes_utils.py
