Metadata-Version: 2.0
Name: py-bes
Version: 0.2.3
Summary: A Python client for accessing the Building Energy Asset Score API
Home-page: https://github.com/GreenBuildingRegistry/py-bes
Author: Paul Munday, Fable Turas
Author-email: paul@paulmunday.net, fable@raintechpdx.com
Maintainer: GreenBuildingRegistry
Maintainer-email: admin@greenbuildingregistry.com
License: UNKNOWN
Keywords: bes,doe,asset score
Platform: UNKNOWN
Classifier: Development Status :: 4 - Beta
Classifier: Intended Audience :: Developers
Classifier: License :: OSI Approved :: BSD License
Classifier: Operating System :: OS Independent
Classifier: Programming Language :: Python :: 2.7
Classifier: Programming Language :: Python :: 3.4
Classifier: Programming Language :: Python :: 3.5
Classifier: Programming Language :: Python :: 3.6
Requires-Dist: frozendict (>=1.2)
Requires-Dist: typing (==3.6.1)
Requires-Dist: requests (==2.13.0)
